Metadata-Version: 1.0
Name: ToxTest
Version: 0.1
Summary: This is an Example Package
Home-page: http://example.com
Author: Victor Jimenez
Author-email: betabandido@gmail.com
License: PSF
Keywords: hello world example examples
Platform: UNKNOWN
